newsmesh/__init__.py
newsmesh/_http.py
newsmesh/_version.py
newsmesh/async_client.py
newsmesh/client.py
newsmesh/exceptions.py
newsmesh/models.py
newsmesh-0.1.0.dist-info/METADATA
newsmesh-0.1.0.dist-info/WHEEL
newsmesh-0.1.0.dist-info/licenses/LICENSE
newsmesh-0.1.0.dist-info/RECORD
