Metadata-Version: 2.4
Name: newsmesh
Version: 0.1.0
Summary: Official Python SDK for the NewsMesh News API
Project-URL: Homepage, https://newsmesh.co
Project-URL: Documentation, https://newsmesh.co/docs
Project-URL: Repository, https://github.com/newsmesh/newsmesh-python
Author-email: NewsMesh <support@newsmesh.co>
License-Expression: MIT
License-File: LICENSE
Keywords: api,articles,news,newsmesh,sdk
Classifier: Development Status :: 4 - Beta
Classifier: Intended Audience :: Developers
Classifier: License :: OSI Approved :: MIT License
Classifier: Operating System :: OS Independent
Classifier: Programming Language :: Python :: 3
Classifier: Programming Language :: Python :: 3.8
Classifier: Programming Language :: Python :: 3.9
Classifier: Programming Language :: Python :: 3.10
Classifier: Programming Language :: Python :: 3.11
Classifier: Programming Language :: Python :: 3.12
Classifier: Typing :: Typed
Requires-Python: >=3.8
Requires-Dist: requests>=2.28.0
Provides-Extra: async
Requires-Dist: aiohttp>=3.8.0; extra == 'async'
Provides-Extra: dev
Requires-Dist: aioresponses>=0.7.0; extra == 'dev'
Requires-Dist: mypy>=1.0.0; extra == 'dev'
Requires-Dist: pytest-asyncio>=0.21.0; extra == 'dev'
Requires-Dist: pytest>=7.0.0; extra == 'dev'
Requires-Dist: responses>=0.23.0; extra == 'dev'
Requires-Dist: ruff>=0.1.0; extra == 'dev'
